LICENSE
MANIFEST.in
setup.py
ttname.1
ttname.1.md
ttname.py
test/test_cli.py
test/test_info.py
test/test_read.py
test/test_write.py
test/util.py
test/data/DejaVuSans.ttf
ttname/__init__.py
ttname/cli.py
ttname/info.py
ttname/table.py
ttname.egg-info/PKG-INFO
ttname.egg-info/SOURCES.txt
ttname.egg-info/dependency_links.txt
ttname.egg-info/entry_points.txt
ttname.egg-info/top_level.txt