Metadata-Version: 1.1
Name: ttname
Version: 1
Summary: CLI font metadata editor
Home-page: https://github.com/tchollingsworth/ttname
Author: T.C. Hollingsworth
Author-email: tchollingsworth@gmail.com
License: BSD
Platform: UNKNOWN
Classifier: Development Status :: 3 - Alpha
Classifier: Environment :: Console
Classifier: License :: OSI Approved :: BSD License
Classifier: Operating System :: OS Independent
Classifier: Topic :: Text Processing :: Fonts
